README.md
setup.cfg
setup.py
test/unit/__init__.py
test/unit/test_airline.py
test/unit/test_amount.py
test/unit/test_any_list_response.py
test/unit/test_base_object.py
test/unit/test_capture_payment_builder.py
test/unit/test_capture_payment_request.py
test/unit/test_client.py
test/unit/test_configuration.py
test/unit/test_confirmation.py
test/unit/test_confirmation_factory.py
test/unit/test_context.py
test/unit/test_credit_card.py
test/unit/test_payment_data.py
test/unit/test_payment_data_factory.py
test/unit/test_payment_facade.py
test/unit/test_payment_request.py
test/unit/test_payment_request_builder.py
test/unit/test_payment_response.py
test/unit/test_receipt.py
test/unit/test_receipt_model.py
test/unit/test_receipt_request.py
test/unit/test_receipt_request_builder.py
test/unit/test_receipt_response.py
test/unit/test_recepient.py
test/unit/test_refund_facade.py
test/unit/test_refund_request.py
test/unit/test_refund_request_builder.py
test/unit/test_refund_response.py
test/unit/test_refund_source.py
test/unit/test_requestor.py
test/unit/test_settings.py
test/unit/test_transfer.py
test/unit/test_transfer_response.py
test/unit/test_user_agent.py
test/unit/test_webhook.py
test/unit/test_webhook_notification.py
yandex_checkout/__init__.py
yandex_checkout/client.py
yandex_checkout/configuration.py
yandex_checkout/payment.py
yandex_checkout/receipt.py
yandex_checkout/refund.py
yandex_checkout/settings.py
yandex_checkout/webhook.py
yandex_checkout/domain/__init__.py
yandex_checkout/domain/common/__init__.py
yandex_checkout/domain/common/base_object.py
yandex_checkout/domain/common/confirmation_type.py
yandex_checkout/domain/common/context.py
yandex_checkout/domain/common/data_context.py
yandex_checkout/domain/common/http_verb.py
yandex_checkout/domain/common/payment_method_type.py
yandex_checkout/domain/common/receipt_type.py
yandex_checkout/domain/common/request_object.py
yandex_checkout/domain/common/response_object.py
yandex_checkout/domain/common/type_factory.py
yandex_checkout_no_uuid.egg-info/PKG-INFO
yandex_checkout_no_uuid.egg-info/SOURCES.txt
yandex_checkout_no_uuid.egg-info/dependency_links.txt
yandex_checkout_no_uuid.egg-info/not-zip-safe
yandex_checkout_no_uuid.egg-info/requires.txt
yandex_checkout_no_uuid.egg-info/top_level.txt